flask_werobot.py
setup.cfg
setup.py
Flask_WeRoBot.egg-info/PKG-INFO
Flask_WeRoBot.egg-info/SOURCES.txt
Flask_WeRoBot.egg-info/dependency_links.txt
Flask_WeRoBot.egg-info/not-zip-safe
Flask_WeRoBot.egg-info/requires.txt
Flask_WeRoBot.egg-info/top_level.txt