Metadata-Version: 1.0
Name: Flask-WeRoBot
Version: 0.1.2
Summary: Writing WeChat Robot by WeRoBot in Flask.
Home-page: https://github.com/whtsky/Flask-WeRoBot
Author: whtsky
Author-email: whtsky@gmail.com
License: BSD
Platform: any
Classifier: Environment :: Web Environment
Classifier: Intended Audience :: Developers
Classifier: License :: OSI Approved :: BSD License
Classifier: Operating System :: OS Independent
Classifier: Programming Language :: Python
Classifier: Topic :: Internet :: WWW/HTTP :: Dynamic Content
Classifier: Topic :: Software Development :: Libraries :: Python Modules
